{
  "version": "7",
  "dialect": "postgresql",
  "entries": [
    {
      "idx": 0,
      "version": "7",
      "when": 1776263578557,
      "tag": "0000_shallow_spiral",
      "breakpoints": true
    },
    {
      "idx": 1,
      "version": "7",
      "when": 1776266101673,
      "tag": "0001_funny_stranger",
      "breakpoints": true
    },
    {
      "idx": 2,
      "version": "7",
      "when": 1776272846325,
      "tag": "0002_boring_bullseye",
      "breakpoints": true
    },
    {
      "idx": 3,
      "version": "7",
      "when": 1776381694821,
      "tag": "0003_lectio_reimagining",
      "breakpoints": true
    }
  ]
}